{
  "db_name": "PostgreSQL",
  "query": "SELECT interval_seconds, last_polled_at\n                       FROM device_login_grants\n                       WHERE device_code_hash = $1",
  "describe": {
    "columns": [
      {
        "ordinal": 0,
        "name": "interval_seconds",
        "type_info": "Int4"
      },
      {
        "ordinal": 1,
        "name": "last_polled_at",
        "type_info": "Timestamptz"
      }
    ],
    "parameters": {
      "Left": [
        "Text"
      ]
    },
    "nullable": [
      false,
      true
    ]
  },
  "hash": "842b4516d4108ad18b299d7d6a7627b2119ccca55d92ca5645a4c891ce881ec6"
}
