{
  "db_name": "PostgreSQL",
  "query": "\n                SELECT content\n                FROM terraform_states\n                WHERE state_id = $1\n                ORDER BY id DESC\n                LIMIT 1\n            ",
  "describe": {
    "columns": [
      {
        "ordinal": 0,
        "name": "content",
        "type_info": "Text"
      }
    ],
    "parameters": {
      "Left": [
        "Text"
      ]
    },
    "nullable": [
      false
    ]
  },
  "hash": "636c553391234678919940840db36394728b5d01f383b7785d71df02b51f5e4a"
}
